decimatr/__init__.py
decimatr/exceptions.py
decimatr/gpu_utils.py
decimatr/metrics.py
decimatr/scheme.py
decimatr/utils.py
decimatr/video_loader.py
decimatr/actors/__init__.py
decimatr/actors/filter_actor.py
decimatr/actors/pipeline.py
decimatr/actors/stateful_actor.py
decimatr/actors/tagger_actor.py
decimatr/core/__init__.py
decimatr/core/processor.py
decimatr/core/temporal_buffer.py
decimatr/filters/__init__.py
decimatr/filters/base.py
decimatr/filters/blur.py
decimatr/filters/diversity.py
decimatr/filters/duplicate.py
decimatr/filters/entropy.py
decimatr/filters/motion.py
decimatr/filters/threshold.py
decimatr/strategies/__init__.py
decimatr/strategies/base.py
decimatr/strategies/blur_removal.py
decimatr/strategies/duplicate_detection.py
decimatr/strategies/smart_sampling.py
decimatr/taggers/__init__.py
decimatr/taggers/base.py
decimatr/taggers/blur.py
decimatr/taggers/clip.py
decimatr/taggers/entropy.py
decimatr/taggers/hash.py
decimatr-0.1.0.dist-info/METADATA
decimatr-0.1.0.dist-info/WHEEL
decimatr-0.1.0.dist-info/licenses/LICENSE
decimatr-0.1.0.dist-info/RECORD
