Metadata-Version: 2.4
Name: decimatr
Version: 0.1.0
Summary: High-performance video frame processing library using actor-based parallel processing
Project-URL: Homepage, https://github.com/DylanLIiii/decimatr
Project-URL: Documentation, https://github.com/DylanLIiii/decimatr
Project-URL: Repository, https://github.com/DylanLIiii/decimatr
Project-URL: Issues, https://github.com/DylanLIiii/decimatr/issues
Project-URL: Changelog, https://github.com/DylanLIiii/decimatr/blob/master/CHANGELOG.md
Author-email: Dylan Li <dylan.h.li@outlook.com>
Maintainer-email: Dylan Li <dylan.h.li@outlook.com>
License: MIT
License-File: LICENSE
Keywords: actor-model,computer-vision,frame-processing,image-processing,parallel-processing,video,video-analysis
Classifier: Development Status :: 3 - Alpha
Classifier: Environment :: GPU :: NVIDIA CUDA
Classifier: Intended Audience :: Developers
Classifier: Intended Audience :: Science/Research
Classifier: License :: OSI Approved :: MIT License
Classifier: Operating System :: OS Independent
Classifier: Programming Language :: Python :: 3
Classifier: Programming Language :: Python :: 3 :: Only
Classifier: Programming Language :: Python :: 3.10
Classifier: Programming Language :: Python :: 3.11
Classifier: Programming Language :: Python :: 3.12
Classifier: Topic :: Multimedia :: Video
Classifier: Topic :: Scientific/Engineering :: Image Processing
Classifier: Topic :: Software Development :: Libraries :: Python Modules
Requires-Python: >=3.10
Requires-Dist: decord>=0.6.0
Requires-Dist: imagehash>=4.3.2
Requires-Dist: loguru>=0.7.3
Requires-Dist: numpy>=2.2.5
Requires-Dist: opencv-python>=4.11.0.86
Requires-Dist: pre-commit>=4.4.0
Requires-Dist: xoscar>=0.3.0
Provides-Extra: dev
Requires-Dist: mypy>=1.0.0; extra == 'dev'
Requires-Dist: pytest-cov>=6.0.0; extra == 'dev'
Requires-Dist: pytest>=8.3.5; extra == 'dev'
Requires-Dist: ruff>=0.8.0; extra == 'dev'
Provides-Extra: gpu
Requires-Dist: open-clip-torch>=2.32.0; extra == 'gpu'
Requires-Dist: torch>=2.0.0; extra == 'gpu'
Requires-Dist: torchvision>=0.15.0; extra == 'gpu'
